soin/__init__.py
soin/base.py
soin/cli.py
soin/job.py
soin/request.py
soin/utils.py
soin-1.0.9.dist-info/entry_points.txt
soin-1.0.9.dist-info/WHEEL
soin-1.0.9.dist-info/METADATA
soin-1.0.9.dist-info/RECORD
