Metadata-Version: 2.1
Name: soin
Version: 1.0.9
Summary: soin is a tool collections for spiders
License: MIT
Author: chenglu
Author-email: chenglu.she@gmail.com
Requires-Python: >=3.7,<4.0
Classifier: License :: OSI Approved :: MIT License
Classifier: Programming Language :: Python :: 3
Classifier: Programming Language :: Python :: 3.10
Classifier: Programming Language :: Python :: 3.7
Classifier: Programming Language :: Python :: 3.8
Classifier: Programming Language :: Python :: 3.9
Requires-Dist: click (>=8.1.3,<9.0.0)
Requires-Dist: redis (>=4.3.4,<5.0.0)
Requires-Dist: requests (>=2.28.1,<3.0.0)
